FIFO.v
module fifo(
    input clk,
    input reset,
    input write_en,
    input read_en,
    input [7:0] data_in,
    output reg [7:0]data_out,
    output full,
    output empty
    );

reg [7:0] mem [0:3];
reg [1:0] rd_ptr;
reg [1:0] wr_ptr;
reg [2:0] count;

assign empty= (count==0);
assign full= (count==4);


always@(posedge clk)
begin

if(reset)
begin
rd_ptr<=0;
wr_ptr<=0;
count<=0;
data_out<=0;
end

else  begin

if(write_en && !full)
begin
mem[wr_ptr]<=data_in;
wr_ptr<=wr_ptr+1;
end

if(read_en&& !empty)
begin
data_out<=mem[rd_ptr];
rd_ptr<=rd_ptr+1;
end

if ((write_en && !full) && !(read_en && !empty))
count <= count + 1;

else if ((read_en && !empty) && !(write_en && !full))
 count <= count - 1;

end

end
endmodule

FIFO_tb.v
`timescale 1ns/1ps

module fifo_tb;

    reg clk;
    reg reset;
    reg write_en;
    reg read_en;
    reg [7:0] data_in;

    wire [7:0] data_out;
    wire full;
    wire empty;
fifo dut (
    .clk(clk),
    .reset(reset),
    .write_en(write_en),
    .read_en(read_en),
    .data_in(data_in),
    .data_out(data_out),
    .full(full),
    .empty(empty)
    );
always #5 clk = ~clk;

initial begin
$dumpfile("fifo.vcd");
$dumpvars(0, fifo_tb);
end

initial begin
    clk      = 0;
    reset    = 1;
    write_en = 0;
    read_en  = 0;
    data_in  = 0;
    #10;
    reset=0;

 data_in = 8'd10;//write
        write_en = 1;
        #10;
 data_in = 8'd20;
        write_en = 1;
        #10;
 data_in = 8'd30;
        write_en = 1;
        #10;
data_in = 8'd40;
        write_en = 1;
        #10;
write_en=0;
#10;

read_en = 1;//read
#10;

#10;

#10;

#10;
read_en = 0;

data_in = 50;
write_en = 1;
read_en = 1;
#10;

write_en = 0;
read_en = 0;
#10;


$finish;
end

initial begin
$monitor("T=%0t | W=%b R=%b | IN=%d OUT=%d | COUNT=%d | FULL=%b EMPTY=%b",
$time, write_en, read_en,data_in, data_out, dut.count, full, empty);
end
endmodule

fifo.vcd
$date
	Thu Aug 20 18:59:35 2026
$end
$version
	Icarus Verilog
$end
$timescale
	1ps
$end
$scope module fifo_tb $end
$var wire 1 ! full $end
$var wire 1 " empty $end
$var wire 8 # data_out [7:0] $end
$var reg 1 $ clk $end
$var reg 8 % data_in [7:0] $end
$var reg 1 & read_en $end
$var reg 1 ' reset $end
$var reg 1 ( write_en $end
$scope module dut $end
$var wire 1 $ clk $end
$var wire 8 ) data_in [7:0] $end
$var wire 1 & read_en $end
$var wire 1 ' reset $end
$var wire 1 ( write_en $end
$var wire 1 ! full $end
$var wire 1 " empty $end
$var reg 3 * count [2:0] $end
$var reg 8 + data_out [7:0] $end
$var reg 2 , rd_ptr [1:0] $end
$var reg 2 - wr_ptr [1:0] $end
$upscope $end
$upscope $end
$enddefinitions $end
$comment Show the parameter values. $end
$dumpall
$end
#0
$dumpvars
bx -
bx ,
bx +
bx *
b0 )
0(
1'
0&
b0 %
0$
bx #
x"
x!
$end
#5000
b0 #
b0 +
1"
0!
b0 *
b0 -
b0 ,
1$
#10000
0$
1(
b1010 %
b1010 )
0'
#15000
0"
b1 *
b1 -
1$
#20000
0$
b10100 %
b10100 )
#25000
b10 *
b10 -
1$
#30000
0$
b11110 %
b11110 )
#35000
b11 *
b11 -
1$
#40000
0$
b101000 %
b101000 )
#45000
1!
b100 *
b0 -
1$
#50000
0$
0(
#55000
1$
#60000
0$
1&
#65000
0!
b11 *
b1 ,
b1010 #
b1010 +
1$
#70000
0$
#75000
b10 *
b10 ,
b10100 #
b10100 +
1$
#80000
0$
#85000
b1 *
b11 ,
b11110 #
b11110 +
1$
#90000
0$
#95000
1"
b0 *
b0 ,
b101000 #
b101000 +
1$
#100000
0$
1(
b110010 %
b110010 )
1&
#105000
0"
b1 *
b1 -
1$
#110000
0$
0&
0(
